{"sections":[{"id":"5","title":"Section 1, Unit 6","words":[{"state":"AVAILABLE","text":"书店","translation":"bookstore","transliteration":"shūdiàn","transliterationObj":{"tokens":[{"token":"书","transliterationTexts":[{"text":"shū","type":"pinyin"}]},{"token":"店","transliterationTexts":[{"text":"diàn","type":"pinyin"}]}]},"tts":"https://d1vq87e9lcf771.cloudfront.net/xiuying/8d3c02ea63e3941a321a21c01b9092f2"}]},{"id":"18","title":"Section 2, Unit 9","words":[{"state":"LOCKED","text":"药店","translation":"pharmacy","transliteration":"yàodiàn","transliterationObj":{"tokens":[{"token":"药","transliterationTexts":[{"text":"yào","type":"pinyin"}]},{"token":"店","transliterationTexts":[{"text":"diàn","type":"pinyin"}]}]},"tts":"https://d1vq87e9lcf771.cloudfront.net/xiuying/f18dbd4a8e7ab425c1c91fc12759c931"}]},{"id":"24","title":"Section 2, Unit 15","words":[{"state":"LOCKED","text":"酒店","translation":"hotel","transliteration":"jiǔdiàn","transliterationObj":{"tokens":[{"token":"酒","transliterationTexts":[{"text":"jiǔ","type":"pinyin"}]},{"token":"店","transliterationTexts":[{"text":"diàn","type":"pinyin"}]}]},"tts":"https://d1vq87e9lcf771.cloudfront.net/xiuying/5077c27bcaa96203acb965db15602738"}]},{"id":"35","title":"Section 2, Unit 26","words":[{"state":"LOCKED","text":"便利店","translation":"convenience store","transliteration":"biànlìdiàn","transliterationObj":{"tokens":[{"token":"便","transliterationTexts":[{"text":"biàn","type":"pinyin"}]},{"token":"利","transliterationTexts":[{"text":"lì","type":"pinyin"}]},{"token":"店","transliterationTexts":[{"text":"diàn","type":"pinyin"}]}]},"tts":"https://d1vq87e9lcf771.cloudfront.net/xiuying/60ccf429896bdb635a3c2074982b6215"}]},{"id":"66","title":"Section 3, Unit 27","words":[{"state":"LOCKED","text":"店","translation":"store","transliteration":"diàn","transliterationObj":{"tokens":[{"token":"店","transliterationTexts":[{"text":"diàn","type":"pinyin"}]}]},"tts":"https://d1vq87e9lcf771.cloudfront.net/xiuying/0d1bb60f1b6678484d84e72d31388ffe"}]},{"id":"126","title":"Section 4, Unit 57","words":[{"state":"LOCKED","text":"理发店","translation":"barbershop","transliteration":"lǐfàdiàn","transliterationObj":{"tokens":[{"token":"理","transliterationTexts":[{"text":"lǐ","type":"pinyin"}]},{"token":"发","transliterationTexts":[{"text":"fà","type":"pinyin"}]},{"token":"店","transliterationTexts":[{"text":"diàn","type":"pinyin"}]}]},"tts":"https://d1vq87e9lcf771.cloudfront.net/xiuying/ee4913596c09e62943cf3868e8f94b48"},{"state":"LOCKED","text":"分店","translation":"branch","transliteration":"fēndiàn","transliterationObj":{"tokens":[{"token":"分","transliterationTexts":[{"text":"fēn","type":"pinyin"}]},{"token":"店","transliterationTexts":[{"text":"diàn","type":"pinyin"}]}]},"tts":"https://d1vq87e9lcf771.cloudfront.net/xiuying/4701a991c5f5a92a7a553e7606c6e8d7"}]}],"strokeData":{"height":109,"paths":["M 53.30,10.63 C 55.72,11.58,60.85,17.78,61.33,19.68","M 25.63,27.23 C 27.15,27.77,29.93,27.86,31.45,27.77 C 47.25,26.86,64.75,23.75,84.56,23.54 C 87.09,23.51,88.61,23.80,89.87,24.07","M 30.49,30.00 C 30.53,31.59,30.53,34.10,30.40,36.38 C 29.50,52.25,27.25,78.25,14.50,90.75","M 57.37,32.88 C 58.01,33.26,59.37,35.71,59.49,36.47 C 59.62,37.23,59.41,66.01,59.28,70.74","M 60.28,51.09 C 67.88,50.46,81.33,47.77,82.39,47.77 C 83.45,47.77,85.35,47.77,86.19,47.98","M 39.24,71.71 C 39.71,72.17,40.19,72.56,40.40,73.14 C 42.03,77.73,43.98,90.40,45.09,98.66","M 41.32,72.86 C 52.82,70.94,76.51,69.25,82.44,68.60 C 84.61,68.36,85.91,70.99,85.60,72.39 C 84.32,78.17,82.71,84.58,80.94,91.92","M 45.55,95.62 C 52.51,94.89,74.27,93.38,83.11,92.65"],"width":109},"title":"店"}