{"sections":[{"id":"41","title":"Section 3, Unit 2","words":[{"state":"LOCKED","text":"眼药水","translation":"eye drops","transliteration":"yǎnyàoshuǐ","transliterationObj":{"tokens":[{"token":"眼","transliterationTexts":[{"text":"yǎn","type":"pinyin"}]},{"token":"药","transliterationTexts":[{"text":"yào","type":"pinyin"}]},{"token":"水","transliterationTexts":[{"text":"shuǐ","type":"pinyin"}]}]},"tts":"https://d1vq87e9lcf771.cloudfront.net/xiuying/120019e27ce1b05c55462d778c9015f0"},{"state":"LOCKED","text":"眼睛","translation":"eye","transliteration":"yǎnjing","transliterationObj":{"tokens":[{"token":"眼","transliterationTexts":[{"text":"yǎn","type":"pinyin"}]},{"token":"睛","transliterationTexts":[{"text":"jing","type":"pinyin"}]}]},"tts":"https://d1vq87e9lcf771.cloudfront.net/xiuying/fe0586cc00e3e2c06080270bcff27cbb"}]},{"id":"48","title":"Section 3, Unit 9","words":[{"state":"LOCKED","text":"眼镜","translation":"glasses","transliteration":"yǎnjìng","transliterationObj":{"tokens":[{"token":"眼","transliterationTexts":[{"text":"yǎn","type":"pinyin"}]},{"token":"镜","transliterationTexts":[{"text":"jìng","type":"pinyin"}]}]},"tts":"https://d1vq87e9lcf771.cloudfront.net/xiuying/3aea4cdbe502b25516d91192607f4411"}]}],"strokeData":{"height":109,"paths":["M 14.88,29.14 C 15.25,30.40,15.80,31.35,15.80,33.03 C 15.80,34.72,15.68,84.57,15.80,86.25","M 16.43,29.66 C 18.55,29.45,34.70,26.75,36.63,26.50 C 38.24,26.29,39.37,27.67,39.37,29.24 C 39.37,35.00,38.62,70.25,38.62,83.41","M 16.39,45.97 C 20.08,45.36,23.78,44.83,27.48,44.35 C 28.48,44.22,29.48,44.10,30.44,43.98","M 16.57,62.47 C 20.00,62.04,23.41,61.51,26.83,61.06 C 27.79,60.93,28.77,60.81,29.75,60.69","M 15.73,81.26 C 21.50,80.50,31.25,79.00,38.54,78.37","M 52.08,20.92 C 54.18,20.80,76.14,17.51,78.05,17.37 C 79.64,17.25,80.66,18.69,80.54,19.40 C 79.50,25.99,76.25,43.40,75.33,46.90","M 52.37,34.20 C 56.51,33.75,60.63,33.10,64.75,32.51 C 65.96,32.34,67.68,32.16,68.85,32.00","M 52.32,47.83 C 59.54,46.92,67.67,45.60,75.51,44.72","M 50.01,18.74 C 50.75,19.50,52.16,21.29,52.16,22.46 C 52.16,42.75,52.16,82.72,51.90,85.56 C 51.66,88.13,50.85,92.12,53.71,90.12 C 56.57,88.12,64.06,80.96,66.44,78.38","M 85.13,47.69 C 85.37,49.12,85.61,49.41,85.61,50.84 C 85.61,52.27,74.37,62.24,72.23,64.25","M 61.52,55.92 C 65.61,55.92,87.04,83.47,90.38,85.53 C 95.19,88.49,95.91,88.49,98.32,89.15"],"width":109},"title":"眼"}