{"sections":[{"id":"85","title":"Section 4, Unit 16","words":[{"state":"LOCKED","text":"有精神","translation":"energetic","transliteration":"yǒujīngshén","transliterationObj":{"tokens":[{"token":"有","transliterationTexts":[{"text":"yǒu","type":"pinyin"}]},{"token":"精","transliterationTexts":[{"text":"jīng","type":"pinyin"}]},{"token":"神","transliterationTexts":[{"text":"shén","type":"pinyin"}]}]},"tts":"https://d1vq87e9lcf771.cloudfront.net/xiuying/67b5c3475778710821fc9f535da57459"}]},{"id":"116","title":"Section 4, Unit 47","words":[{"state":"LOCKED","text":"神秘","translation":"mysterious","transliteration":"shénmì","transliterationObj":{"tokens":[{"token":"神","transliterationTexts":[{"text":"shén","type":"pinyin"}]},{"token":"秘","transliterationTexts":[{"text":"mì","type":"pinyin"}]}]},"tts":"https://d1vq87e9lcf771.cloudfront.net/xiuying/08f537053aedd0bc5b195770a93a10bf"}]}],"strokeData":{"height":109,"paths":["M 27.50,16.25 C 30.83,18.07,34.75,21.25,36.75,23.75","M 14.25,39.00 C 16.25,39.75,17.39,39.81,19.50,39.50 C 23.75,38.88,32.50,36.75,37.00,35.25 C 39.48,34.42,40.89,36.43,39.50,38.75 C 34.25,47.50,22.00,62.25,10.25,70.25","M 31.43,51.87 C 32.16,52.60,32.81,53.65,32.81,55.51 C 32.81,65.32,32.83,81.25,32.83,89.13 C 32.83,91.29,32.83,92.85,32.83,93.50","M 33.75,50.62 C 38.26,53.23,44.13,57.67,48.00,62.24","M 51.50,30.24 C 52.38,31.12,53.12,32.24,53.23,33.00 C 54.25,40.12,55.77,51.05,56.66,61.36 C 56.77,62.63,56.87,63.89,56.95,65.13","M 53.94,31.67 C 68.52,29.28,82.55,27.00,90.89,26.22 C 94.53,25.88,97.12,27.03,96.68,31.02 C 96.02,36.95,94.29,48.46,92.34,57.27 C 92.10,58.34,91.86,59.37,91.62,60.34","M 56.21,45.72 C 59.73,45.42,89.88,42.50,94.07,42.25","M 58.01,61.78 C 68.00,61.00,79.00,59.75,90.80,59.18","M 72.87,10.25 C 73.94,11.31,74.58,13.00,74.58,14.75 C 74.58,18.38,74.41,70.03,74.37,92.25 C 74.36,95.28,74.36,97.76,74.36,99.50"],"width":109},"title":"神"}