{"sections":[{"id":"1","title":"Section 1, Unit 2","words":[{"state":"AVAILABLE","text":"你呢","translation":"how about you","transliteration":"nǐne","transliterationObj":{"tokens":[{"token":"你","transliterationTexts":[{"text":"nǐ","type":"pinyin"}]},{"token":"呢","transliterationTexts":[{"text":"ne","type":"pinyin"}]}]},"tts":"https://d1vq87e9lcf771.cloudfront.net/xiuying/1077a9a77d9799012fd81d27edaefdcf"}]},{"id":"2","title":"Section 1, Unit 3","words":[{"state":"AVAILABLE","text":"你","translation":"you","transliteration":"nǐ","transliterationObj":{"tokens":[{"token":"你","transliterationTexts":[{"text":"nǐ","type":"pinyin"}]}]},"tts":"https://d1vq87e9lcf771.cloudfront.net/xiuying/e93a85e46fde6e7e250f965a64fdc368"}]},{"id":"8","title":"Section 1, Unit 9","words":[{"state":"LOCKED","text":"你好","translation":"hello","transliteration":"nǐhǎo","transliterationObj":{"tokens":[{"token":"你","transliterationTexts":[{"text":"nǐ","type":"pinyin"}]},{"token":"好","transliterationTexts":[{"text":"hǎo","type":"pinyin"}]}]},"tts":"https://d1vq87e9lcf771.cloudfront.net/xiuying/c7e1b80f689e9e38d65a087c47c384d1"}]},{"id":"9","title":"Section 1, Unit 10","words":[{"state":"LOCKED","text":"你们","translation":"you all","transliteration":"nǐmen","transliterationObj":{"tokens":[{"token":"你","transliterationTexts":[{"text":"nǐ","type":"pinyin"}]},{"token":"们","transliterationTexts":[{"text":"men","type":"pinyin"}]}]},"tts":"https://d1vq87e9lcf771.cloudfront.net/xiuying/ef4639f61f83d17bc062636e79fc88b3"}]},{"id":"48","title":"Section 3, Unit 9","words":[{"state":"LOCKED","text":"很高兴认识你","translation":null,"transliteration":"hěngāoxìngrènshinǐ","transliterationObj":{"tokens":[{"token":"很","transliterationTexts":[{"text":"hěn","type":"pinyin"}]},{"token":"高","transliterationTexts":[{"text":"gāo","type":"pinyin"}]},{"token":"兴","transliterationTexts":[{"text":"xìng","type":"pinyin"}]},{"token":"认","transliterationTexts":[{"text":"rèn","type":"pinyin"}]},{"token":"识","transliterationTexts":[{"text":"shi","type":"pinyin"}]},{"token":"你","transliterationTexts":[{"text":"nǐ","type":"pinyin"}]}]},"tts":"https://d1vq87e9lcf771.cloudfront.net/xiuying/1c1caa986679d6433934898c89d1b5f8"}]},{"id":"86","title":"Section 4, Unit 17","words":[{"state":"LOCKED","text":"你觉得呢","translation":"What do you think?","transliteration":"nǐjuédene","transliterationObj":{"tokens":[{"token":"你","transliterationTexts":[{"text":"nǐ","type":"pinyin"}]},{"token":"觉","transliterationTexts":[{"text":"jué","type":"pinyin"}]},{"token":"得","transliterationTexts":[{"text":"de","type":"pinyin"}]},{"token":"呢","transliterationTexts":[{"text":"ne","type":"pinyin"}]}]},"tts":"https://d1vq87e9lcf771.cloudfront.net/xiuying/e7549f792145c85bbeab9ecf5b5601ab"}]},{"id":"95","title":"Section 4, Unit 26","words":[{"state":"LOCKED","text":"祝你好运","translation":"Good luck","transliteration":"zhùnǐhǎoyùn","transliterationObj":{"tokens":[{"token":"祝","transliterationTexts":[{"text":"zhù","type":"pinyin"}]},{"token":"你","transliterationTexts":[{"text":"nǐ","type":"pinyin"}]},{"token":"好","transliterationTexts":[{"text":"hǎo","type":"pinyin"}]},{"token":"运","transliterationTexts":[{"text":"yùn","type":"pinyin"}]}]},"tts":"https://d1vq87e9lcf771.cloudfront.net/xiuying/347d7daac8f652ebfc2923feeab106e7"}]}],"strokeData":{"height":109,"paths":["M 33.64,16.76 C 33.81,18.56,33.59,20.22,33.05,21.76 C 29.57,32.49,20.45,43.31,13.13,53.66","M 25.18,40.00 C 26.01,40.92,26.31,42.38,26.31,43.50 C 26.34,54.17,26.46,75.56,26.51,88.87 C 26.52,91.36,26.53,93.39,26.53,94.75","M 55.32,14.39 C 55.42,15.82,55.43,17.01,54.90,18.37 C 52.00,25.77,45.13,39.08,36.49,47.76","M 49.75,31.93 C 51.85,32.64,53.68,32.38,55.83,32.03 C 65.87,30.38,73.26,28.68,87.42,27.50 C 93.93,26.80,91.76,29.58,87.46,42.82","M 64.34,40.70 C 65.44,41.75,65.68,42.88,65.68,45.24 C 65.68,57.22,65.57,85.05,65.57,89.13 C 65.57,98.39,59.26,89.94,57.97,88.91","M 49.39,59.75 C 49.49,61.08,49.49,62.16,48.98,63.42 C 47.23,67.75,44.04,74.71,39.99,80.17","M 81.10,58.13 C 84.43,62.08,89.71,74.37,90.54,80.52"],"width":109},"title":"你"}